{
     "goodsList": [
        {
            "goodsID": 45,
            "goodsNum": "5",
            "goodsDec": {
                "code": {
                    "1": "红",
                    "2": "黄",
                    "3": "M",
                    "4": "L",
                    "5": "XL",
                    "6": "A",
                    "7": "B"
                },
                "price": {
                    "1": {
                        "3": {
                            "6": 100
                        }
                    }
                }
            }
        }
    ]
}
